MANIFEST.in
setup.py
bin/testhello321
testhello321/BaseWidget.py
testhello321/__init__.py
testhello321/_version.py
testhello321/all_widgets.py
testhello321/host_widget.py
testhello321/init.py
testhello321/reactopyacolabwidget.py
testhello321/reactopyacomponent.py
testhello321/reactopyaelectronwidget.py
testhello321/reactopyahostedwidget.py
testhello321/shellscript.py
testhello321.egg-info/PKG-INFO
testhello321.egg-info/SOURCES.txt
testhello321.egg-info/dependency_links.txt
testhello321.egg-info/requires.txt
testhello321.egg-info/top_level.txt
testhello321/electron/src/ReactopyaModel.js
testhello321/electron/src/index.js
testhello321/electron/src/preload.js
testhello321/electron/web/index.html
testhello321/widgets/__init__.py
testhello321/widgets/index.js
testhello321/widgets/HelloWidget/HelloWidget.js
testhello321/widgets/HelloWidget/HelloWidget.json
testhello321/widgets/HelloWidget/HelloWidget.py
testhello321/widgets/HelloWidget/__init__.py