Metadata-Version: 1.1
Name: testhello321
Version: 0.1.0
Summary: hello
Home-page: UNKNOWN
Author: Elias
Author-email: UNKNOWN
License: UNKNOWN
Platform: UNKNOWN
Classifier: Programming Language :: Python :: 3
Classifier: License :: OSI Approved :: Apache Software License
Classifier: Operating System :: OS Independent
